sotb_wrapper-2.0.2.data/data/include/sotb/fmod/opt_ptrn.mod
sotb_wrapper-2.0.2.data/data/include/sotb/fmod/seiscope_optimization_toolbox.mod
sotb_wrapper-2.0.2.data/data/include/sotb/fmod/opt_trn.mod
sotb_wrapper-2.0.2.data/data/include/sotb/fmod/miscellaneous.mod
sotb_wrapper-2.0.2.data/data/include/sotb/fmod/opt_plbfgs.mod
sotb_wrapper-2.0.2.data/data/include/sotb/fmod/opt_pnlcg.mod
sotb_wrapper-2.0.2.data/data/include/sotb/fmod/opt_pstd.mod
sotb_wrapper-2.0.2.data/data/include/sotb/fmod/typedef.mod
sotb_wrapper-2.0.2.data/data/include/sotb/fmod/opt_lbfgs.mod
sotb_wrapper.libs/libquadmath-96973f99.so.0.0.0
sotb_wrapper.libs/libgfortran-040039e1.so.5.0.0
sotb_wrapper/test_PTRN
sotb_wrapper/test_PSTD
sotb_wrapper/test_TRN
sotb_wrapper/interface.py
sotb_wrapper/test_LBFGS
sotb_wrapper/test_PLBFGS
sotb_wrapper/__init__.py
sotb_wrapper/_version.py
sotb_wrapper/libsotb.so
sotb_wrapper/test_PNLCG
sotb_wrapper-2.0.2.dist-info/top_level.txt
sotb_wrapper-2.0.2.dist-info/METADATA
sotb_wrapper-2.0.2.dist-info/LICENSE.md
sotb_wrapper-2.0.2.dist-info/RECORD
sotb_wrapper-2.0.2.dist-info/WHEEL
