Metadata-Version: 2.1
Name: sotb-wrapper
Version: 2.0.2
Summary: wrapper to call fortran routines from SEISCOPE optimization toolbox
Home-page: https://github.com/ofmla/seiscope_opt_toolbox_w_ctypes
Author: Oscar Mojica
Author-email: o_mojical@hotmail.com
License: MIT
License-File: LICENSE.md
Requires-Dist: numpy (>=1.20)
